[{"kind": "Listing", "data": {"modhash": "", "whitelist_status": "all_ads", "children": [{"kind": "t3", "data": {"domain": "youtube.com", "approved_at_utc": null, "banned_by": null, "media_embed": {}, "thumbnail_width": 70, "subreddit": "milliondollarextreme", "selftext_html": null, "selftext": "", "likes": null, "suggested_sort": null, "user_reports": [], "secure_media": null, "is_reddit_media_domain": false, "link_flair_text": null, "id": "25snle", "banned_at_utc": null, "view_count": null, "archived": true, "clicked": false, "report_reasons": null, "title": "round bread?", "num_crossposts": 0, "saved": false, "can_mod_post": false, "is_crosspostable": false, "pinned": false, "score": 12, "approved_by": null, "over_18": false, "hidden": false, "num_comments": 9, "thumbnail": "https://c.thumbs.redditmedia.com/s3J4FlDBEzRIHpab.jpg", "subreddit_id": "t5_2vsta", "hide_score": false, "edited": false, "link_flair_css_class": null, "author_flair_css_class": null, "contest_mode": false, "gilded": 0, "locked": false, "downs": 0, "brand_safe": true, "secure_media_embed": {}, "removal_reason": null, "can_gild": false, "thumbnail_height": 70, "parent_whitelist_status": "all_ads", "name": "t3_25snle", "spoiler": false, "permalink": "/r/milliondollarextreme/comments/25snle/round_bread/", "num_reports": null, "whitelist_status": "all_ads", "stickied": false, "created": 1400369318.0, "url": "http://www.youtube.com/attribution_link?a=pI0hvHcaO6U&amp;u=%2Fwatch%3Fv%3D-SXTIuYzVfQ%26feature%3Dshare", "author_flair_text": null, "quarantine": false, "author": "ElusiveParadox16", "created_utc": 1400340518.0, "subreddit_name_prefixed": "r/milliondollarextreme", "distinguished": null, "media": null, "upvote_ratio": 0.89, "mod_reports": [], "is_self": false, "visited": false, "subreddit_type": "public", "is_video": false, "ups": 12}}], "after": null, "before": null}}, {"kind": "Listing", "data": {"modhash": "", "whitelist_status": "all_ads", "children": [{"kind": "t1", "data": {"subreddit_id": "t5_2vsta", "approved_at_utc": null, "banned_by": null, "removal_reason": null, "link_id": "t3_25snle", "likes": null, "replies": {"kind": "Listing", "data": {"modhash": "", "whitelist_status": "all_ads", "children": [{"kind": "t1", "data": {"subreddit_id": "t5_2vsta", "approved_at_utc": null, "banned_by": null, "removal_reason": null, "link_id": "t3_25snle", "likes": null, "replies": {"kind": "Listing", "data": {"modhash": "", "whitelist_status": "all_ads", "children": [{"kind": "t1", "data": {"subreddit_id": "t5_2vsta", "approved_at_utc": null, "banned_by": null, "removal_reason": null, "link_id": "t3_25snle", "likes": null, "replies": {"kind": "Listing", "data": {"modhash": "", "whitelist_status": "all_ads", "children": [{"kind": "t1", "data": {"subreddit_id": "t5_2vsta", "approved_at_utc": null, "banned_by": null, "removal_reason": null, "link_id": "t3_25snle", "likes": null, "replies": "", "user_reports": [], "saved": false, "id": "chknr8r", "banned_at_utc": null, "gilded": 0, "archived": true, "report_reasons": null, "author": "iamjakeparty", "can_mod_post": false, "ups": 0, "parent_id": "t1_chkmogt", "score": 0, "approved_by": null, "downs": 0, "body": "Thanks goy, got me feelin real good right now.", "edited": false, "author_flair_css_class": null, "collapsed": false, "is_submitter": false, "collapsed_reason": null, "body_html": "&lt;div class=\"md\"&gt;&lt;p&gt;Thanks goy, got me feelin real good right now.&lt;/p&gt;\n&lt;/div&gt;", "stickied": false, "can_gild": true, "subreddit": "milliondollarextreme", "score_hidden": false, "permalink": "/r/milliondollarextreme/comments/25snle/round_bread/chknr8r/", "subreddit_type": "public", "name": "t1_chknr8r", "created": 1400401619.0, "author_flair_text": null, "created_utc": 1400372819.0, "subreddit_name_prefixed": "r/milliondollarextreme", "controversiality": 1, "depth": 3, "mod_reports": [], "num_reports": null, "distinguished": null}}], "after": null, "before": null}}, "user_reports": [], "saved": false, "id": "chkmogt", "banned_at_utc": null, "gilded": 0, "archived": true, "report_reasons": null, "author": "mypenisisbigasfuck", "can_mod_post": false, "ups": 7, "parent_id": "t1_chkhswa", "score": 7, "approved_by": null, "downs": 0, "body": "haha! Goy, like the jews say! Classic!!!", "edited": false, "author_flair_css_class": null, "collapsed": false, "is_submitter": false, "collapsed_reason": null, "body_html": "&lt;div class=\"md\"&gt;&lt;p&gt;haha! Goy, like the jews say! Classic!!!&lt;/p&gt;\n&lt;/div&gt;", "stickied": false, "can_gild": true, "subreddit": "milliondollarextreme", "score_hidden": false, "permalink": "/r/milliondollarextreme/comments/25snle/round_bread/chkmogt/", "subreddit_type": "public", "name": "t1_chkmogt", "created": 1400398408.0, "author_flair_text": null, "created_utc": 1400369608.0, "subreddit_name_prefixed": "r/milliondollarextreme", "controversiality": 0, "depth": 2, "mod_reports": [], "num_reports": null, "distinguished": null}}, {"kind": "t1", "data": {"subreddit_id": "t5_2vsta", "approved_at_utc": null, "banned_by": null, "removal_reason": null, "link_id": "t3_25snle", "likes": null, "replies": {"kind": "Listing", "data": {"modhash": "", "whitelist_status": "all_ads", "children": [{"kind": "t1", "data": {"subreddit_id": "t5_2vsta", "approved_at_utc": null, "banned_by": null, "removal_reason": null, "link_id": "t3_25snle", "likes": null, "replies": {"kind": "Listing", "data": {"modhash": "", "whitelist_status": "all_ads", "children": [{"kind": "t1", "data": {"subreddit_id": "t5_2vsta", "approved_at_utc": null, "banned_by": null, "removal_reason": null, "link_id": "t3_25snle", "likes": null, "replies": {"kind": "Listing", "data": {"modhash": "", "whitelist_status": "all_ads", "children": [{"kind": "t1", "data": {"subreddit_id": "t5_2vsta", "approved_at_utc": null, "banned_by": null, "removal_reason": null, "link_id": "t3_25snle", "likes": null, "replies": {"kind": "Listing", "data": {"modhash": "", "whitelist_status": "all_ads", "children": [{"kind": "t1", "data": {"subreddit_id": "t5_2vsta", "approved_at_utc": null, "banned_by": null, "removal_reason": null, "link_id": "t3_25snle", "likes": null, "replies": "", "user_reports": [], "saved": false, "id": "chkqqeo", "banned_at_utc": null, "gilded": 0, "archived": true, "report_reasons": null, "author": "ElusiveParadox16", "can_mod_post": false, "ups": -3, "parent_id": "t1_chkqo8y", "score": -3, "approved_by": null, "downs": 0, "body": "I bet you wish you knew where I live,  idiot", "edited": false, "author_flair_css_class": null, "collapsed": false, "is_submitter": true, "collapsed_reason": null, "body_html": "&lt;div class=\"md\"&gt;&lt;p&gt;I bet you wish you knew where I live,  idiot&lt;/p&gt;\n&lt;/div&gt;", "stickied": false, "can_gild": true, "subreddit": "milliondollarextreme", "score_hidden": false, "permalink": "/r/milliondollarextreme/comments/25snle/round_bread/chkqqeo/", "subreddit_type": "public", "name": "t1_chkqqeo", "created": 1400410417.0, "author_flair_text": null, "created_utc": 1400381617.0, "subreddit_name_prefixed": "r/milliondollarextreme", "controversiality": 0, "depth": 6, "mod_reports": [], "num_reports": null, "distinguished": null}}], "after": null, "before": null}}, "user_reports": [], "saved": false, "id": "chkqo8y", "banned_at_utc": null, "gilded": 0, "archived": true, "report_reasons": null, "author": "iamjakeparty", "can_mod_post": false, "ups": 5, "parent_id": "t1_chkqmg5", "score": 5, "approved_by": null, "downs": 0, "body": "You're gonna regret this, I'm gonna make you regret this.", "edited": false, "author_flair_css_class": null, "collapsed": false, "is_submitter": false, "collapsed_reason": null, "body_html": "&lt;div class=\"md\"&gt;&lt;p&gt;You&amp;#39;re gonna regret this, I&amp;#39;m gonna make you regret this.&lt;/p&gt;\n&lt;/div&gt;", "stickied": false, "can_gild": true, "subreddit": "milliondollarextreme", "score_hidden": false, "permalink": "/r/milliondollarextreme/comments/25snle/round_bread/chkqo8y/", "subreddit_type": "public", "name": "t1_chkqo8y", "created": 1400410238.0, "author_flair_text": null, "created_utc": 1400381438.0, "subreddit_name_prefixed": "r/milliondollarextreme", "controversiality": 0, "depth": 5, "mod_reports": [], "num_reports": null, "distinguished": null}}], "after": null, "before": null}}, "user_reports": [], "saved": false, "id": "chkqmg5", "banned_at_utc": null, "gilded": 0, "archived": true, "report_reasons": null, "author": "ElusiveParadox16", "can_mod_post": false, "ups": -3, "parent_id": "t1_chkp2bi", "score": -3, "approved_by": null, "downs": 0, "body": "We're on the Internet,  I'm not scared of anything or anybody. Come fight me in real life faggot. ", "edited": false, "author_flair_css_class": null, "collapsed": false, "is_submitter": true, "collapsed_reason": null, "body_html": "&lt;div class=\"md\"&gt;&lt;p&gt;We&amp;#39;re on the Internet,  I&amp;#39;m not scared of anything or anybody. Come fight me in real life faggot. &lt;/p&gt;\n&lt;/div&gt;", "stickied": false, "can_gild": true, "subreddit": "milliondollarextreme", "score_hidden": false, "permalink": "/r/milliondollarextreme/comments/25snle/round_bread/chkqmg5/", "subreddit_type": "public", "name": "t1_chkqmg5", "created": 1400410093.0, "author_flair_text": null, "created_utc": 1400381293.0, "subreddit_name_prefixed": "r/milliondollarextreme", "controversiality": 0, "depth": 4, "mod_reports": [], "num_reports": null, "distinguished": null}}], "after": null, "before": null}}, "user_reports": [], "saved": false, "id": "chkp2bi", "banned_at_utc": null, "gilded": 0, "archived": true, "report_reasons": null, "author": "iamjakeparty", "can_mod_post": false, "ups": 2, "parent_id": "t1_chkow1u", "score": 2, "approved_by": null, "downs": 0, "body": "I'm gonna fuck you up so bad tonight.", "edited": false, "author_flair_css_class": null, "collapsed": false, "is_submitter": false, "collapsed_reason": null, "body_html": "&lt;div class=\"md\"&gt;&lt;p&gt;I&amp;#39;m gonna fuck you up so bad tonight.&lt;/p&gt;\n&lt;/div&gt;", "stickied": false, "can_gild": true, "subreddit": "milliondollarextreme", "score_hidden": false, "permalink": "/r/milliondollarextreme/comments/25snle/round_bread/chkp2bi/", "subreddit_type": "public", "name": "t1_chkp2bi", "created": 1400405468.0, "author_flair_text": null, "created_utc": 1400376668.0, "subreddit_name_prefixed": "r/milliondollarextreme", "controversiality": 0, "depth": 3, "mod_reports": [], "num_reports": null, "distinguished": null}}], "after": null, "before": null}}, "user_reports": [], "saved": false, "id": "chkow1u", "banned_at_utc": null, "gilded": 0, "archived": true, "report_reasons": null, "author": "ElusiveParadox16", "can_mod_post": false, "ups": -2, "parent_id": "t1_chkhswa", "score": -2, "approved_by": null, "downs": 0, "body": "Man you're soooo fonny, I wish I was as fonny as you \"goy\".\nSee, I'm Jewish too", "edited": false, "author_flair_css_class": null, "collapsed": false, "is_submitter": true, "collapsed_reason": null, "body_html": "&lt;div class=\"md\"&gt;&lt;p&gt;Man you&amp;#39;re soooo fonny, I wish I was as fonny as you &amp;quot;goy&amp;quot;.\nSee, I&amp;#39;m Jewish too&lt;/p&gt;\n&lt;/div&gt;", "stickied": false, "can_gild": true, "subreddit": "milliondollarextreme", "score_hidden": false, "permalink": "/r/milliondollarextreme/comments/25snle/round_bread/chkow1u/", "subreddit_type": "public", "name": "t1_chkow1u", "created": 1400404948.0, "author_flair_text": null, "created_utc": 1400376148.0, "subreddit_name_prefixed": "r/milliondollarextreme", "controversiality": 1, "depth": 2, "mod_reports": [], "num_reports": null, "distinguished": null}}], "after": null, "before": null}}, "user_reports": [], "saved": false, "id": "chkhswa", "banned_at_utc": null, "gilded": 0, "archived": true, "report_reasons": null, "author": "iamjakeparty", "can_mod_post": false, "ups": -2, "parent_id": "t1_chkc0w0", "score": -2, "approved_by": null, "downs": 0, "body": "Like we don't know? Fuck off goy.", "edited": false, "author_flair_css_class": null, "collapsed": false, "is_submitter": false, "collapsed_reason": null, "body_html": "&lt;div class=\"md\"&gt;&lt;p&gt;Like we don&amp;#39;t know? Fuck off goy.&lt;/p&gt;\n&lt;/div&gt;", "stickied": false, "can_gild": true, "subreddit": "milliondollarextreme", "score_hidden": false, "permalink": "/r/milliondollarextreme/comments/25snle/round_bread/chkhswa/", "subreddit_type": "public", "name": "t1_chkhswa", "created": 1400384524.0, "author_flair_text": null, "created_utc": 1400355724.0, "subreddit_name_prefixed": "r/milliondollarextreme", "controversiality": 1, "depth": 1, "mod_reports": [], "num_reports": null, "distinguished": null}}], "after": null, "before": null}}, "user_reports": [], "saved": false, "id": "chkc0w0", "banned_at_utc": null, "gilded": 0, "archived": true, "report_reasons": null, "author": "ElusiveParadox16", "can_mod_post": false, "ups": 1, "parent_id": "t3_25snle", "score": 1, "approved_by": null, "downs": 0, "body": "This is the 17th day in the Thirty Days of Hyde!!!", "edited": false, "author_flair_css_class": null, "collapsed": false, "is_submitter": true, "collapsed_reason": null, "body_html": "&lt;div class=\"md\"&gt;&lt;p&gt;This is the 17th day in the Thirty Days of Hyde!!!&lt;/p&gt;\n&lt;/div&gt;", "stickied": false, "can_gild": true, "subreddit": "milliondollarextreme", "score_hidden": false, "permalink": "/r/milliondollarextreme/comments/25snle/round_bread/chkc0w0/", "subreddit_type": "public", "name": "t1_chkc0w0", "created": 1400369390.0, "author_flair_text": null, "created_utc": 1400340590.0, "subreddit_name_prefixed": "r/milliondollarextreme", "controversiality": 1, "depth": 0, "mod_reports": [], "num_reports": null, "distinguished": null}}], "after": null, "before": null}}]