[{"kind": "Listing", "data": {"modhash": "", "whitelist_status": "all_ads", "children": [{"kind": "t3", "data": {"domain": "i.redd.it", "approved_at_utc": null, "banned_by": null, "media_embed": {}, "thumbnail_width": 140, "subreddit": "milliondollarextreme", "selftext_html": null, "selftext": "", "likes": null, "suggested_sort": null, "user_reports": [], "secure_media": null, "is_reddit_media_domain": true, "link_flair_text": null, "id": "64ke5c", "banned_at_utc": null, "view_count": null, "archived": true, "clicked": false, "report_reasons": null, "title": "kindly requesting some more anti-british humour. Thanks!", "num_crossposts": 0, "saved": false, "can_mod_post": false, "is_crosspostable": false, "pinned": false, "score": 1, "approved_by": null, "over_18": false, "hidden": false, "preview": {"images": [{"source": {"url": "https://i.redditmedia.com/xgQr84il853W2MpMydOjqStdsGUazofPkoUN6WSL3jc.jpg?s=904f2438383927b54c6d04eb6c60e4f5", "width": 300, "height": 300}, "resolutions": [{"url": "https://i.redditmedia.com/xgQr84il853W2MpMydOjqStdsGUazofPkoUN6WSL3jc.jpg?fit=crop&amp;crop=faces%2Centropy&amp;arh=2&amp;w=108&amp;s=236af253261835d09b7cf423f588419f", "width": 108, "height": 108}, {"url": "https://i.redditmedia.com/xgQr84il853W2MpMydOjqStdsGUazofPkoUN6WSL3jc.jpg?fit=crop&amp;crop=faces%2Centropy&amp;arh=2&amp;w=216&amp;s=40c30b99f09bff26c0a348c176b37b23", "width": 216, "height": 216}], "variants": {}, "id": "IVopkx6ixWhC7phlJJP_ulu-HPJwLrwKeGg4QKl_9-c"}], "enabled": true}, "num_comments": 7, "thumbnail": "https://b.thumbs.redditmedia.com/uvxBkTn0RYDsB_BpA2XcQ9c0gHf7bXvhLCQQC-D3G6A.jpg", "subreddit_id": "t5_2vsta", "hide_score": false, "edited": false, "link_flair_css_class": null, "author_flair_css_class": null, "contest_mode": false, "gilded": 0, "locked": false, "downs": 0, "brand_safe": true, "secure_media_embed": {}, "removal_reason": null, "post_hint": "image", "can_gild": false, "thumbnail_height": 140, "parent_whitelist_status": "all_ads", "name": "t3_64ke5c", "spoiler": false, "permalink": "/r/milliondollarextreme/comments/64ke5c/kindly_requesting_some_more_antibritish_humour/", "num_reports": null, "whitelist_status": "all_ads", "stickied": false, "created": 1491868287.0, "url": "https://i.redd.it/qtdu4j85zqqy.jpg", "author_flair_text": null, "quarantine": false, "author": "leditor999888", "created_utc": 1491839487.0, "subreddit_name_prefixed": "r/milliondollarextreme", "distinguished": null, "media": null, "upvote_ratio": 0.54, "mod_reports": [], "is_self": false, "visited": false, "subreddit_type": "public", "is_video": false, "ups": 1}}], "after": null, "before": null}}, {"kind": "Listing", "data": {"modhash": "", "whitelist_status": "all_ads", "children": [{"kind": "t1", "data": {"subreddit_id": "t5_2vsta", "approved_at_utc": null, "banned_by": null, "removal_reason": null, "link_id": "t3_64ke5c", "likes": null, "replies": "", "user_reports": [], "saved": false, "id": "dg33iyc", "banned_at_utc": null, "gilded": 0, "archived": true, "report_reasons": null, "author": "nuggetsoftruth", "can_mod_post": false, "ups": 9, "parent_id": "t3_64ke5c", "score": 9, "approved_by": null, "downs": 0, "body": "https://i.yuki.la/pol/1458404127906.jpg", "edited": false, "author_flair_css_class": null, "collapsed": false, "is_submitter": false, "collapsed_reason": null, "body_html": "&lt;div class=\"md\"&gt;&lt;p&gt;&lt;a href=\"https://i.yuki.la/pol/1458404127906.jpg\"&gt;https://i.yuki.la/pol/1458404127906.jpg&lt;/a&gt;&lt;/p&gt;\n&lt;/div&gt;", "stickied": false, "can_gild": true, "subreddit": "milliondollarextreme", "score_hidden": false, "permalink": "/r/milliondollarextreme/comments/64ke5c/kindly_requesting_some_more_antibritish_humour/dg33iyc/", "subreddit_type": "public", "name": "t1_dg33iyc", "created": 1491880322.0, "author_flair_text": null, "created_utc": 1491851522.0, "subreddit_name_prefixed": "r/milliondollarextreme", "controversiality": 0, "depth": 0, "mod_reports": [], "num_reports": null, "distinguished": null}}, {"kind": "t1", "data": {"subreddit_id": "t5_2vsta", "approved_at_utc": null, "banned_by": null, "removal_reason": null, "link_id": "t3_64ke5c", "likes": null, "replies": "", "user_reports": [], "saved": false, "id": "dg35vs7", "banned_at_utc": null, "gilded": 0, "archived": true, "report_reasons": null, "author": "TT900", "can_mod_post": false, "ups": 4, "parent_id": "t3_64ke5c", "score": 4, "approved_by": null, "downs": 0, "body": "terrorism is part and parcel of living in a big city", "edited": false, "author_flair_css_class": "", "collapsed": false, "is_submitter": false, "collapsed_reason": null, "body_html": "&lt;div class=\"md\"&gt;&lt;p&gt;terrorism is part and parcel of living in a big city&lt;/p&gt;\n&lt;/div&gt;", "stickied": false, "can_gild": true, "subreddit": "milliondollarextreme", "score_hidden": false, "permalink": "/r/milliondollarextreme/comments/64ke5c/kindly_requesting_some_more_antibritish_humour/dg35vs7/", "subreddit_type": "public", "name": "t1_dg35vs7", "created": 1491882777.0, "author_flair_text": "\u212c\u2113\u2134\u2134\u2202\u211e\u028a\u03b7\u03b7\u03b5\u0491\u03df", "created_utc": 1491853977.0, "subreddit_name_prefixed": "r/milliondollarextreme", "controversiality": 0, "depth": 0, "mod_reports": [], "num_reports": null, "distinguished": null}}, {"kind": "t1", "data": {"subreddit_id": "t5_2vsta", "approved_at_utc": null, "banned_by": null, "removal_reason": null, "link_id": "t3_64ke5c", "likes": null, "replies": "", "user_reports": [], "saved": false, "id": "dg334r4", "banned_at_utc": null, "gilded": 0, "archived": true, "report_reasons": null, "author": "sellmethispenis", "can_mod_post": false, "ups": 1, "parent_id": "t3_64ke5c", "score": 1, "approved_by": null, "downs": 0, "body": "u fackin wot m8? check out kays good cooking ", "edited": false, "author_flair_css_class": "", "collapsed": false, "is_submitter": false, "collapsed_reason": null, "body_html": "&lt;div class=\"md\"&gt;&lt;p&gt;u fackin wot m8? check out kays good cooking &lt;/p&gt;\n&lt;/div&gt;", "stickied": false, "can_gild": true, "subreddit": "milliondollarextreme", "score_hidden": false, "permalink": "/r/milliondollarextreme/comments/64ke5c/kindly_requesting_some_more_antibritish_humour/dg334r4/", "subreddit_type": "public", "name": "t1_dg334r4", "created": 1491879908.0, "author_flair_text": "headache", "created_utc": 1491851108.0, "subreddit_name_prefixed": "r/milliondollarextreme", "controversiality": 0, "depth": 0, "mod_reports": [], "num_reports": null, "distinguished": null}}, {"kind": "t1", "data": {"subreddit_id": "t5_2vsta", "approved_at_utc": null, "banned_by": null, "removal_reason": null, "link_id": "t3_64ke5c", "likes": null, "replies": "", "user_reports": [], "saved": false, "id": "dg3cjye", "banned_at_utc": null, "gilded": 0, "archived": true, "report_reasons": null, "author": "xL02DzD24G0NzSL4Y32x", "can_mod_post": false, "ups": 1, "parent_id": "t3_64ke5c", "score": 1, "approved_by": null, "downs": 0, "body": "[Mfw](http://crooksandliars.com/files/primary_image/17/01/nip000204951795_1037800c.jpg) I have to buy a 6 month contract for a VPN just to look at softcore porn and beat my uncircumcised dick. ", "edited": false, "author_flair_css_class": "", "collapsed": false, "is_submitter": false, "collapsed_reason": null, "body_html": "&lt;div class=\"md\"&gt;&lt;p&gt;&lt;a href=\"http://crooksandliars.com/files/primary_image/17/01/nip000204951795_1037800c.jpg\"&gt;Mfw&lt;/a&gt; I have to buy a 6 month contract for a VPN just to look at softcore porn and beat my uncircumcised dick. &lt;/p&gt;\n&lt;/div&gt;", "stickied": false, "can_gild": true, "subreddit": "milliondollarextreme", "score_hidden": false, "permalink": "/r/milliondollarextreme/comments/64ke5c/kindly_requesting_some_more_antibritish_humour/dg3cjye/", "subreddit_type": "public", "name": "t1_dg3cjye", "created": 1491890006.0, "author_flair_text": "Devout Muslim", "created_utc": 1491861206.0, "subreddit_name_prefixed": "r/milliondollarextreme", "controversiality": 0, "depth": 0, "mod_reports": [], "num_reports": null, "distinguished": null}}, {"kind": "t1", "data": {"subreddit_id": "t5_2vsta", "approved_at_utc": null, "banned_by": null, "removal_reason": null, "link_id": "t3_64ke5c", "likes": null, "replies": "", "user_reports": [], "saved": false, "id": "dg3gga6", "banned_at_utc": null, "gilded": 0, "archived": true, "report_reasons": null, "author": "ShamalamanPanda", "can_mod_post": false, "ups": 1, "parent_id": "t3_64ke5c", "score": 1, "approved_by": null, "downs": 0, "body": "tesco \n\ntelly licenses", "edited": false, "author_flair_css_class": "", "collapsed": false, "is_submitter": false, "collapsed_reason": null, "body_html": "&lt;div class=\"md\"&gt;&lt;p&gt;tesco &lt;/p&gt;\n\n&lt;p&gt;telly licenses&lt;/p&gt;\n&lt;/div&gt;", "stickied": false, "can_gild": true, "subreddit": "milliondollarextreme", "score_hidden": false, "permalink": "/r/milliondollarextreme/comments/64ke5c/kindly_requesting_some_more_antibritish_humour/dg3gga6/", "subreddit_type": "public", "name": "t1_dg3gga6", "created": 1491894917.0, "author_flair_text": "read evola", "created_utc": 1491866117.0, "subreddit_name_prefixed": "r/milliondollarextreme", "controversiality": 0, "depth": 0, "mod_reports": [], "num_reports": null, "distinguished": null}}, {"kind": "t1", "data": {"subreddit_id": "t5_2vsta", "approved_at_utc": null, "banned_by": null, "removal_reason": null, "link_id": "t3_64ke5c", "likes": null, "replies": {"kind": "Listing", "data": {"modhash": "", "whitelist_status": "all_ads", "children": [{"kind": "t1", "data": {"subreddit_id": "t5_2vsta", "approved_at_utc": null, "banned_by": null, "removal_reason": null, "link_id": "t3_64ke5c", "likes": null, "replies": "", "user_reports": [], "saved": false, "id": "dg43doo", "banned_at_utc": null, "gilded": 0, "archived": true, "report_reasons": null, "author": "leditor999888", "can_mod_post": false, "ups": 1, "parent_id": "t1_dg41h4r", "score": 1, "approved_by": null, "downs": 0, "body": "at least you are not southern fairies", "edited": false, "author_flair_css_class": null, "collapsed": false, "is_submitter": true, "collapsed_reason": null, "body_html": "&lt;div class=\"md\"&gt;&lt;p&gt;at least you are not southern fairies&lt;/p&gt;\n&lt;/div&gt;", "stickied": false, "can_gild": true, "subreddit": "milliondollarextreme", "score_hidden": false, "permalink": "/r/milliondollarextreme/comments/64ke5c/kindly_requesting_some_more_antibritish_humour/dg43doo/", "subreddit_type": "public", "name": "t1_dg43doo", "created": 1491935411.0, "author_flair_text": null, "created_utc": 1491906611.0, "subreddit_name_prefixed": "r/milliondollarextreme", "controversiality": 0, "depth": 1, "mod_reports": [], "num_reports": null, "distinguished": null}}], "after": null, "before": null}}, "user_reports": [], "saved": false, "id": "dg41h4r", "banned_at_utc": null, "gilded": 0, "archived": true, "report_reasons": null, "author": "Randythegeologist", "can_mod_post": false, "ups": 1, "parent_id": "t3_64ke5c", "score": 1, "approved_by": null, "downs": 0, "body": "I'm British and come from a small northern provincial town where people were exactly like the stereotypes you see get goofed on AMA [M8]", "edited": false, "author_flair_css_class": "", "collapsed": false, "is_submitter": false, "collapsed_reason": null, "body_html": "&lt;div class=\"md\"&gt;&lt;p&gt;I&amp;#39;m British and come from a small northern provincial town where people were exactly like the stereotypes you see get goofed on AMA [M8]&lt;/p&gt;\n&lt;/div&gt;", "stickied": false, "can_gild": true, "subreddit": "milliondollarextreme", "score_hidden": false, "permalink": "/r/milliondollarextreme/comments/64ke5c/kindly_requesting_some_more_antibritish_humour/dg41h4r/", "subreddit_type": "public", "name": "t1_dg41h4r", "created": 1491929473.0, "author_flair_text": "Peanut Arbuckle", "created_utc": 1491900673.0, "subreddit_name_prefixed": "r/milliondollarextreme", "controversiality": 0, "depth": 0, "mod_reports": [], "num_reports": null, "distinguished": null}}], "after": null, "before": null}}]